cli.py
dbtt-0.1.2.dist-info/LICENSE
dbtt-0.1.2.dist-info/METADATA
dbtt-0.1.2.dist-info/WHEEL
dbtt-0.1.2.dist-info/entry_points.txt
dbtt-0.1.2.dist-info/top_level.txt
dbtt-0.1.2.dist-info/RECORD
